anipics/__init__.py
anipics/models.py
anipics/services/__init__.py
anipics/services/animepicsx.py
anipics/services/nekoslife.py
anipics/services/purrbot.py
anipics/services/waifupics.py
anipics-1.5.5.dist-info/LICENSE
anipics-1.5.5.dist-info/METADATA
anipics-1.5.5.dist-info/WHEEL
anipics-1.5.5.dist-info/RECORD
